grass_gis_chatbot/__init__.py
grass_sample_chatbot-0.1.dist-info/METADATA
grass_sample_chatbot-0.1.dist-info/WHEEL
grass_sample_chatbot-0.1.dist-info/top_level.txt
grass_sample_chatbot-0.1.dist-info/RECORD
