Metadata-Version: 2.1
Name: grass-sample-chatbot
Version: 0.1
Summary: A sample chatbot for GRASS GIS based on T5-small model
Author: Sachintha Nadeeshan
Author-email: snkodikara52@gmail.com
Classifier: Programming Language :: Python :: 3
Classifier: Operating System :: OS Independent
Requires-Python: >=3.6
Requires-Dist: torch
Requires-Dist: transformers
Requires-Dist: gradio
